[
  {
    "id": "pretest_cs101_e7dcbccc",
    "courseId": "cs101",
    "questions": [
      {
        "id": "q1",
        "question": "Which of the following best describes the core of computer science?",
        "options": [
          "The study of computer hardware and its manufacturing.",
          "The study of computation, algorithms, and information.",
          "The practice of building websites and mobile applications.",
          "The design and development of operating systems exclusively."
        ],
        "correctAnswer": 1,
        "topicId": "topic_1_1",
        "topicTitle": "What is Computer Science?"
      },
      {
        "id": "q2",
        "question": "What is a key design philosophy of the Go programming language that makes it appealing for beginners?",
        "options": [
          "Extreme flexibility and a vast number of features.",
          "Simplicity and ease of learning.",
          "Heavy reliance on complex object-oriented paradigms.",
          "Extensive use of manual memory management."
        ],
        "correctAnswer": 1,
        "topicId": "topic_1_2",
        "topicTitle": "Introduction to the Go Programming Language"
      },
      {
        "id": "q3",
        "question": "Which of the following is a fundamental command-line operation for navigating directories in a terminal?",
        "options": [
          "ls",
          "cd",
          "mkdir",
          "rm"
        ],
        "correctAnswer": 1,
        "topicId": "topic_1_3",
        "topicTitle": "Setting up Your Development Environment (VS Code & Terminal)"
      },
      {
        "id": "q4",
        "question": "In a basic Go program, which package must always be imported to run an executable program?",
        "options": [
          "fmt",
          "errors",
          "main",
          "os"
        ],
        "correctAnswer": 2,
        "topicId": "topic_1_4",
        "topicTitle": "Your First Go Program: 'Hello, World!'"
      },
      {
        "id": "q5",
        "question": "What is the fundamental difference between `int` and `uint` data types in Go?",
        "options": [
          "`int` can store floating-point numbers, `uint` cannot.",
          "`int` can store negative numbers, `uint` cannot.",
          "`uint` has a larger range than `int`.",
          "`int` uses more memory than `uint`."
        ],
        "correctAnswer": 1,
        "topicId": "topic_2_1",
        "topicTitle": "Understanding Data Types (Integers, Floats, Booleans)"
      },
      {
        "id": "q6",
        "question": "Which of the following Go syntax examples correctly declares and initializes a variable named `count` with the integer value 10?",
        "options": [
          "var count = 10",
          "count := 10",
          "let count = 10",
          "count = 10"
        ],
        "correctAnswer": 1,
        "topicId": "topic_2_2",
        "topicTitle": "Declaring and Using Variables"
      },
      {
        "id": "q7",
        "question": "What keyword is used in Go to declare a constant value that cannot be changed during program execution?",
        "options": [
          "var",
          "let",
          "const",
          "final"
        ],
        "correctAnswer": 2,
        "topicId": "topic_2_3",
        "topicTitle": "Constants and Their Usage"
      },
      {
        "id": "q8",
        "question": "In Go, which operator is used to check if two values are *not* equal?",
        "options": [
          "==",
          "!=",
          "===",
          "=/="
        ],
        "correctAnswer": 1,
        "topicId": "topic_2_4",
        "topicTitle": "Basic Arithmetic and Logical Operators"
      },
      {
        "id": "q9",
        "question": "Consider the following Go code snippet. What will be printed to the console if `score` is 85?",
        "options": [
          "A",
          "B",
          "C",
          "Nothing"
        ],
        "correctAnswer": 1,
        "topicId": "topic_3_1",
        "topicTitle": "Conditional Statements: `if`, `else if`, `else`"
      },
      {
        "id": "q10",
        "question": "What is the primary function of the `break` statement within a loop in Go?",
        "options": [
          "To start the next iteration of the loop immediately.",
          "To terminate the loop entirely.",
          "To skip the current iteration and proceed to the next.",
          "To declare a new variable within the loop."
        ],
        "correctAnswer": 1,
        "topicId": "topic_3_4",
        "topicTitle": "`break` and `continue` Statements"
      },
      {
        "id": "q11",
        "question": "What is a key characteristic of Go arrays?",
        "options": [
          "They can dynamically resize after creation.",
          "Their size is fixed at the time of declaration.",
          "They can store elements of different data types.",
          "They are primarily used for key-value storage."
        ],
        "correctAnswer": 1,
        "topicId": "topic_4_1",
        "topicTitle": "Arrays in Go"
      },
      {
        "id": "q12",
        "question": "Which of the following is NOT a core component of a Go slice?",
        "options": [
          "Pointer to the underlying array",
          "Length of the slice",
          "Capacity of the slice",
          "Key for accessing elements"
        ],
        "correctAnswer": 3,
        "topicId": "topic_4_2",
        "topicTitle": "Introduction to Slices"
      },
      {
        "id": "q13",
        "question": "When using `append` to add an element to a slice, what might happen if the slice's capacity is exceeded?",
        "options": [
          "The program will immediately crash.",
          "A new underlying array will be allocated, and elements copied.",
          "The new element will be ignored.",
          "The original slice remains unchanged and the element is lost."
        ],
        "correctAnswer": 1,
        "topicId": "topic_4_3",
        "topicTitle": "Slice Operations: `append` and `copy`"
      },
      {
        "id": "q14",
        "question": "In Go, what is the primary purpose of a `map`?",
        "options": [
          "To store ordered sequences of elements.",
          "To represent fixed-size collections of elements.",
          "To store key-value pairs.",
          "To define custom data structures with named fields."
        ],
        "correctAnswer": 2,
        "topicId": "topic_5_1",
        "topicTitle": "Maps in Go"
      },
      {
        "id": "q15",
        "question": "What keyword is used in Go to define a custom data type that groups related fields together?",
        "options": [
          "type",
          "struct",
          "class",
          "enum"
        ],
        "correctAnswer": 1,
        "topicId": "topic_5_2",
        "topicTitle": "Structs: Defining Custom Data Types"
      },
      {
        "id": "q16",
        "question": "In Go, how are functions defined to accept a variable number of arguments of the same type?",
        "options": [
          "Using a fixed-size array.",
          "Using pointers to a slice.",
          "Using a variadic parameter indicated by `...`.",
          "By explicitly listing all possible arguments."
        ],
        "correctAnswer": 2,
        "topicId": "topic_6_2",
        "topicTitle": "Variadic Functions and Anonymous Functions"
      },
      {
        "id": "q17",
        "question": "How does Go typically handle errors returned from functions?",
        "options": [
          "By throwing exceptions that need to be caught.",
          "By returning an `error` type as the last return value.",
          "By printing error messages directly to the console.",
          "By panicking the program execution."
        ],
        "correctAnswer": 1,
        "topicId": "topic_6_3",
        "topicTitle": "Introduction to Error Handling in Go"
      },
      {
        "id": "q18",
        "question": "What does a pointer variable in Go store?",
        "options": [
          "The actual value of a variable.",
          "The memory address of another variable.",
          "A copy of the data type.",
          "The length of a data structure."
        ],
        "correctAnswer": 1,
        "topicId": "topic_7_1",
        "topicTitle": "Understanding Pointers"
      },
      {
        "id": "q19",
        "question": "When you pass a variable to a function in Go by default, what happens?",
        "options": [
          "The function receives a reference to the original variable.",
          "The function receives a copy of the original variable's value.",
          "The function receives a pointer to the original variable.",
          "The function can modify the original variable directly without any special syntax."
        ],
        "correctAnswer": 1,
        "topicId": "topic_7_4",
        "topicTitle": "Pass by Value vs. Pass by Reference (and Go's Approach)"
      },
      {
        "id": "q20",
        "question": "In Go, an `interface` defines a set of methods. A type satisfies an interface if it implements all of those methods. This is known as:",
        "options": [
          "Explicit interface implementation.",
          "Structural typing or duck typing.",
          "Nominal typing.",
          "Inheritance-based polymorphism."
        ],
        "correctAnswer": 1,
        "topicId": "topic_8_2",
        "topicTitle": "Implementing Interfaces Implicitly"
      },
      {
        "id": "q21",
        "question": "What is the primary benefit of using `goroutines` in Go?",
        "options": [
          "They are heavyweight threads that consume significant resources.",
          "They allow for the execution of functions concurrently and are very lightweight.",
          "They are exclusively used for handling user interface events.",
          "They are designed for single-threaded execution of tasks."
        ],
        "correctAnswer": 1,
        "topicId": "topic_9_2",
        "topicTitle": "Goroutines: Lightweight Threads"
      },
      {
        "id": "q22",
        "question": "What is the main purpose of `channels` in Go concurrency?",
        "options": [
          "To store large amounts of data efficiently.",
          "To facilitate communication and synchronization between goroutines.",
          "To define the structure of data types.",
          "To manage file input and output operations."
        ],
        "correctAnswer": 1,
        "topicId": "topic_9_3",
        "topicTitle": "Channels: Communicating Between Goroutines"
      },
      {
        "id": "q23",
        "question": "What is Go's `package` system primarily used for?",
        "options": [
          "Defining executable entry points for applications.",
          "Organizing and reusing code into logical units.",
          "Managing external dependencies between projects.",
          "Specifying the graphical user interface framework."
        ],
        "correctAnswer": 1,
        "topicId": "topic_10_1",
        "topicTitle": "Understanding Go Packages"
      },
      {
        "id": "q24",
        "question": "Which file is central to Go Modules for managing project dependencies?",
        "options": [
          "main.go",
          "go.mod",
          "config.json",
          "package.json"
        ],
        "correctAnswer": 1,
        "topicId": "topic_10_2",
        "topicTitle": "Go Modules: Dependency Management"
      },
      {
        "id": "q25",
        "question": "What is the concept of an `algorithm` in computer science?",
        "options": [
          "A piece of hardware that performs calculations.",
          "A specific programming language syntax.",
          "A step-by-step procedure or set of rules for solving a problem.",
          "A way to design graphical user interfaces."
        ],
        "correctAnswer": 2,
        "topicId": "topic_11_1",
        "topicTitle": "What are Algorithms?"
      },
      {
        "id": "q26",
        "question": "Big O notation is used to describe:",
        "options": [
          "The exact execution time of an algorithm in milliseconds.",
          "The memory usage of a program.",
          "The performance of an algorithm in terms of how its resource usage scales with input size.",
          "The number of lines of code in a program."
        ],
        "correctAnswer": 2,
        "topicId": "topic_11_3",
        "topicTitle": "Time and Space Complexity (Big O Notation - Basic)"
      },
      {
        "id": "q27",
        "question": "What is the primary goal of a `code review` in software development?",
        "options": [
          "To automatically generate documentation for the code.",
          "To identify potential bugs, improve code quality, and share knowledge.",
          "To compile the code into an executable program.",
          "To perform extensive performance benchmarking."
        ],
        "correctAnswer": 1,
        "topicId": "topic_12_1",
        "topicTitle": "Project Work and Code Review"
      },
      {
        "id": "q28",
        "question": "Which of the following is a common debugging technique?",
        "options": [
          "Adding print statements to track variable values.",
          "Ignoring error messages.",
          "Running the program once and expecting it to work.",
          "Only testing with happy path scenarios."
        ],
        "correctAnswer": 0,
        "topicId": "topic_12_2",
        "topicTitle": "Debugging Techniques in Go"
      },
      {
        "id": "q29",
        "question": "What is the purpose of writing `unit tests` in Go?",
        "options": [
          "To test the entire application's functionality at once.",
          "To verify that small, isolated pieces of code (units) function as expected.",
          "To automatically deploy the application to production.",
          "To design the user interface of the application."
        ],
        "correctAnswer": 1,
        "topicId": "topic_12_3",
        "topicTitle": "Introduction to Testing in Go"
      }
    ],
    "createdAt": "2025-11-17T15:29:44.724384Z",
    "maxScore": 29
  }
]